dbxdeploy/DbxDeployBundle.py
dbxdeploy/DbxDeployBundleTest.py
dbxdeploy/_config/.gitignore
dbxdeploy/_config/config.yaml
dbxdeploy/_config/config_test.yaml
dbxdeploy/black/BlackChecker.py
dbxdeploy/cluster/ClusterRestarter.py
dbxdeploy/dbc/CommandConverter.py
dbxdeploy/dbc/CommandConverterTest.py
dbxdeploy/dbc/CommandsConverter.py
dbxdeploy/dbc/CommandsConverterTest.py
dbxdeploy/dbc/DbcCreator.py
dbxdeploy/dbc/DbcNotebookConverter.py
dbxdeploy/dbc/DbcUploader.py
dbxdeploy/dbc/PathsPreparer.py
dbxdeploy/dbc/PathsPreparerTest.py
dbxdeploy/dbfs/DbfsFileDownloader.py
dbxdeploy/dbfs/DbfsFileUploader.py
dbxdeploy/dbfs/DbfsUploadCommand.py
dbxdeploy/deploy/CurrentAndReleaseDeployer.py
dbxdeploy/deploy/DependencyBuilderCommand.py
dbxdeploy/deploy/DeployCommand.py
dbxdeploy/deploy/DeployJobSubmitCommand.py
dbxdeploy/deploy/Deployer.py
dbxdeploy/deploy/DeployerJobSubmitter.py
dbxdeploy/deploy/LocalPathsResolver.py
dbxdeploy/deploy/MasterPackageBuilder.py
dbxdeploy/deploy/MasterPackageDeployer.py
dbxdeploy/deploy/ReleaseCommand.py
dbxdeploy/deploy/Releaser.py
dbxdeploy/deploy/TargetPathsResolver.py
dbxdeploy/deploy/WorkingDirFactory.py
dbxdeploy/filesystem/utils.py
dbxdeploy/git/CurrentBranchResolver.py
dbxdeploy/git/CurrentRepositoryFactory.py
dbxdeploy/job/JobCreator.py
dbxdeploy/job/JobGetter.py
dbxdeploy/job/JobSubmitter.py
dbxdeploy/job/JobsCreatorAndRunner.py
dbxdeploy/job/JobsDeleter.py
dbxdeploy/job/JobsDeleterCommand.py
dbxdeploy/job/NotebookKiller.py
dbxdeploy/job/RunJobCommand.py
dbxdeploy/job/RunsGetter.py
dbxdeploy/notebook/CurrentDirectoryUpdater.py
dbxdeploy/notebook/Notebook.py
dbxdeploy/notebook/NotebooksDeployer.py
dbxdeploy/notebook/NotebooksLocator.py
dbxdeploy/notebook/RelativePathResolver.py
dbxdeploy/notebook/converter/CellsExtractor.py
dbxdeploy/notebook/converter/CommandSeparatorConverter.py
dbxdeploy/notebook/converter/DbcScriptRenderer.py
dbxdeploy/notebook/converter/JinjaTemplateLoader.py
dbxdeploy/notebook/converter/NotebookConverterInterface.py
dbx_deploy-1.4.1.dist-info/entry_points.txt
dbx_deploy-1.4.1.dist-info/LICENSE
dbx_deploy-1.4.1.dist-info/WHEEL
dbx_deploy-1.4.1.dist-info/METADATA
dbx_deploy-1.4.1.dist-info/RECORD
